aidrac/__init__.py
aidrac-0.2.0.dist-info/METADATA
aidrac-0.2.0.dist-info/WHEEL
aidrac-0.2.0.dist-info/RECORD
