Metadata-Version: 2.4
Name: aidrac
Version: 0.2.0
Summary: AIdrac - AI Out-of-Band Management with Sentinel AI. Alias for mcp-server-aidrac.
Project-URL: Homepage, https://humotica.com
Author-email: Jasper van de Meent <jasper@humotica.com>, Root AI <root_ai@humotica.nl>
License-Expression: AGPL-3.0-or-later
Keywords: aidrac,dtmf,hardware-guardian,idrac,ilo,ipmi,oob,sentinel,ultrasonic
Classifier: Development Status :: 3 - Alpha
Classifier: License :: OSI Approved :: GNU Affero General Public License v3 or later (AGPLv3+)
Classifier: Programming Language :: Python :: 3
Requires-Python: >=3.10
Requires-Dist: mcp-server-aidrac>=0.2.0
